AUTHORS
ChangeLog
MANIFEST.in
README.rst
requirements.txt
setup.cfg
setup.py
leonardo_module_folio/__init__.py
leonardo_module_folio/admin.py
leonardo_module_folio/models.py
leonardo_module_folio/views.py
leonardo_module_folio.egg-info/PKG-INFO
leonardo_module_folio.egg-info/SOURCES.txt
leonardo_module_folio.egg-info/dependency_links.txt
leonardo_module_folio.egg-info/not-zip-safe
leonardo_module_folio.egg-info/pbr.json
leonardo_module_folio.egg-info/top_level.txt
leonardo_module_folio/apps/__init__.py
leonardo_module_folio/apps/folio.py
leonardo_module_folio/locale/cs/LC_MESSAGES/django.po
leonardo_module_folio/locale/de/LC_MESSAGES/django.po
leonardo_module_folio/locale/sk/LC_MESSAGES/django.po
leonardo_module_folio/migrations/0001_initial.py
leonardo_module_folio/migrations/__init__.py
leonardo_module_folio/templates/folio/project_detail.html
leonardo_module_folio/templates/folio/project_list.html
leonardo_module_folio/templates/widget/featuredprojects/_item.html
leonardo_module_folio/templates/widget/featuredprojects/default.html
leonardo_module_folio/templates/widget/projectcategories/_item.html
leonardo_module_folio/templates/widget/projectcategories/default.html
leonardo_module_folio/widget/__init__.py
leonardo_module_folio/widget/featuredprojects/__init__.py
leonardo_module_folio/widget/featuredprojects/models.py
leonardo_module_folio/widget/projectcategories/__init__.py
leonardo_module_folio/widget/projectcategories/models.py